tinyLDAP3/__init__.py
tinyLDAP3/client.py
tinyLDAP3/decorators.py
tinyLDAP3/exceptions.py
tinyLDAP3/logger.py
tinyLDAP3/models.py
tinyLDAP3-0.2.61.dist-info/LICENSE
tinyLDAP3-0.2.61.dist-info/METADATA
tinyLDAP3-0.2.61.dist-info/WHEEL
tinyLDAP3-0.2.61.dist-info/top_level.txt
tinyLDAP3-0.2.61.dist-info/RECORD
