Metadata-Version: 2.1
Name: tinyLDAP3
Version: 0.2.61
Summary: Tiny wrapper for Python ldap3 Package.
Author-email: Luarvick <lu.luarvick@gmail.com>
Project-URL: Homepage, https://github.com/luarvick/tinyLDAP3
Project-URL: Issues, https://github.com/luarvick/tinyLDAP3/issues
Classifier: Programming Language :: Python :: 3
Classifier: License :: OSI Approved :: MIT License
Classifier: Operating System :: OS Independent
Requires-Python: >=3.10
License-File: LICENSE
Requires-Dist: ldap3==2.9.1
Requires-Dist: pydantic==2.6.3
